translate.py
trcli_za-0.1.0.dist-info/METADATA
trcli_za-0.1.0.dist-info/WHEEL
trcli_za-0.1.0.dist-info/entry_points.txt
trcli_za-0.1.0.dist-info/top_level.txt
trcli_za-0.1.0.dist-info/RECORD
